[{"birth_weight_recode12":"01","mother_bmi_recode":"1","mother_age_recode9":"2","f_count":10,"m_count":9},{"birth_weight_recode12":"01","mother_bmi_recode":"1","mother_age_recode9":"3","f_count":23,"m_count":27},{"birth_weight_recode12":"01","mother_bmi_recode":"1","mother_age_recode9":"4","f_count":18,"m_count":24},{"birth_weight_recode12":"01","mother_bmi_recode":"1","mother_age_recode9":"5","f_count":18,"m_count":10},{"birth_weight_recode12":"01","mother_bmi_recode":"1","mother_age_recode9":"6","f_count":7,"m_count":3},{"birth_weight_recode12":"01","mother_bmi_recode":"2","mother_age_recode9":"2","f_count":72,"m_count":89},{"birth_weight_recode12":"01","mother_bmi_recode":"2","mother_age_recode9":"3","f_count":170,"m_count":197},{"birth_weight_recode12":"01","mother_bmi_recode":"2","mother_age_recode9":"4","f_count":212,"m_count":217},{"birth_weight_recode12":"01","mother_bmi_recode":"2","mother_age_recode9":"5","f_count":196,"m_count":175},{"birth_weight_recode12":"01","mother_bmi_recode":"2","mother_age_recode9":"6","f_count":98,"m_count":104},{"birth_weight_recode12":"01","mother_bmi_recode":"2","mother_age_recode9":"7","f_count":22,"m_count":17},{"birth_weight_recode12":"01","mother_bmi_recode":"2","mother_age_recode9":"8","f_count":1,"m_count":4},{"birth_weight_recode12":"01","mother_bmi_recode":"3","mother_age_recode9":"2","f_count":31,"m_count":40},{"birth_weight_recode12":"01","mother_bmi_recode":"3","mother_age_recode9":"3","f_count":108,"m_count":141},{"birth_weight_recode12":"01","mother_bmi_recode":"3","mother_age_recode9":"4","f_count":143,"m_count":153},{"birth_weight_recode12":"01","mother_bmi_recode":"3","mother_age_recode9":"5","f_count":173,"m_count":183},{"birth_weight_recode12":"01","mother_bmi_recode":"3","mother_age_recode9":"6","f_count":96,"m_count":90},{"birth_weight_recode12":"01","mother_bmi_recode":"3","mother_age_recode9":"7","f_count":30,"m_count":18},{"birth_weight_recode12":"01","mother_bmi_recode":"3","mother_age_recode9":"8","f_count":3,"m_count":3},{"birth_weight_recode12":"01","mother_bmi_recode":"4","mother_age_recode9":"2","f_count":21,"m_count":33},{"birth_weight_recode12":"01","mother_bmi_recode":"4","mother_age_recode9":"3","f_count":108,"m_count":92},{"birth_weight_recode12":"01","mother_bmi_recode":"4","mother_age_recode9":"4","f_count":123,"m_count":149},{"birth_weight_recode12":"01","mother_bmi_recode":"4","mother_age_recode9":"5","f_count":109,"m_count":128},{"birth_weight_recode12":"01","mother_bmi_recode":"4","mother_age_recode9":"6","f_count":83,"m_count":57},{"birth_weight_recode12":"01","mother_bmi_recode":"4","mother_age_recode9":"7","f_count":22,"m_count":11},{"birth_weight_recode12":"01","mother_bmi_recode":"5","mother_age_recode9":"2","f_count":14,"m_count":7},{"birth_weight_recode12":"01","mother_bmi_recode":"5","mother_age_recode9":"3","f_count":50,"m_count":62},{"birth_weight_recode12":"01","mother_bmi_recode":"5","mother_age_recode9":"4","f_count":80,"m_count":103},{"birth_weight_recode12":"01","mother_bmi_recode":"5","mother_age_recode9":"5","f_count":61,"m_count":70},{"birth_weight_recode12":"01","mother_bmi_recode":"5","mother_age_recode9":"6","f_count":65,"m_count":52},{"birth_weight_recode12":"01","mother_bmi_recode":"5","mother_age_recode9":"7","f_count":11,"m_count":6},{"birth_weight_recode12":"01","mother_bmi_recode":"6","mother_age_recode9":"2","f_count":11,"m_count":11},{"birth_weight_recode12":"01","mother_bmi_recode":"6","mother_age_recode9":"3","f_count":40,"m_count":48},{"birth_weight_recode12":"01","mother_bmi_recode":"6","mother_age_recode9":"4","f_count":68,"m_count":77},{"birth_weight_recode12":"01","mother_bmi_recode":"6","mother_age_recode9":"5","f_count":75,"m_count":69},{"birth_weight_recode12":"01","mother_bmi_recode":"6","mother_age_recode9":"6","f_count":27,"m_count":26},{"birth_weight_recode12":"01","mother_bmi_recode":"6","mother_age_recode9":"7","f_count":15,"m_count":7},{"birth_weight_recode12":"01","mother_bmi_recode":"9","mother_age_recode9":"2","f_count":18,"m_count":21},{"birth_weight_recode12":"01","mother_bmi_recode":"9","mother_age_recode9":"3","f_count":55,"m_count":74},{"birth_weight_recode12":"01","mother_bmi_recode":"9","mother_age_recode9":"4","f_count":74,"m_count":88},{"birth_weight_recode12":"01","mother_bmi_recode":"9","mother_age_recode9":"5","f_count":57,"m_count":61},{"birth_weight_recode12":"01","mother_bmi_recode":"9","mother_age_recode9":"6","f_count":34,"m_count":45},{"birth_weight_recode12":"01","mother_bmi_recode":"9","mother_age_recode9":"7","f_count":9,"m_count":7},{"birth_weight_recode12":"02","mother_bmi_recode":"1","mother_age_recode9":"1","f_count":3,"m_count":1},{"birth_weight_recode12":"02","mother_bmi_recode":"1","mother_age_recode9":"2","f_count":43,"m_count":59},{"birth_weight_recode12":"02","mother_bmi_recode":"1","mother_age_recode9":"3","f_count":120,"m_count":103},{"birth_weight_recode12":"02","mother_bmi_recode":"1","mother_age_recode9":"4","f_count":87,"m_count":80},{"birth_weight_recode12":"02","mother_bmi_recode":"1","mother_age_recode9":"5","f_count":57,"m_count":59},{"birth_weight_recode12":"02","mother_bmi_recode":"1","mother_age_recode9":"6","f_count":14,"m_count":30},{"birth_weight_recode12":"02","mother_bmi_recode":"1","mother_age_recode9":"7","f_count":4,"m_count":6},{"birth_weight_recode12":"02","mother_bmi_recode":"2","mother_age_recode9":"1","f_count":4,"m_count":2},{"birth_weight_recode12":"02","mother_bmi_recode":"2","mother_age_recode9":"2","f_count":310,"m_count":302},{"birth_weight_recode12":"02","mother_bmi_recode":"2","mother_age_recode9":"3","f_count":719,"m_count":700},{"birth_weight_recode12":"02","mother_bmi_recode":"2","mother_age_recode9":"4","f_count":850,"m_count":924},{"birth_weight_recode12":"02","mother_bmi_recode":"2","mother_age_recode9":"5","f_count":729,"m_count":762},{"birth_weight_recode12":"02","mother_bmi_recode":"2","mother_age_recode9":"6","f_count":428,"m_count":443},{"birth_weight_recode12":"02","mother_bmi_recode":"2","mother_age_recode9":"7","f_count":103,"m_count":110},{"birth_weight_recode12":"02","mother_bmi_recode":"2","mother_age_recode9":"8","f_count":18,"m_count":19},{"birth_weight_recode12":"02","mother_bmi_recode":"2","mother_age_recode9":"9","f_count":3,"m_count":3},{"birth_weight_recode12":"02","mother_bmi_recode":"3","mother_age_recode9":"1","f_count":4,"m_count":4},{"birth_weight_recode12":"02","mother_bmi_recode":"3","mother_age_recode9":"2","f_count":133,"m_count":158},{"birth_weight_recode12":"02","mother_bmi_recode":"3","mother_age_recode9":"3","f_count":422,"m_count":494},{"birth_weight_recode12":"02","mother_bmi_recode":"3","mother_age_recode9":"4","f_count":599,"m_count":641},{"birth_weight_recode12":"02","mother_bmi_recode":"3","mother_age_recode9":"5","f_count":620,"m_count":615},{"birth_weight_recode12":"02","mother_bmi_recode":"3","mother_age_recode9":"6","f_count":389,"m_count":409},{"birth_weight_recode12":"02","mother_bmi_recode":"3","mother_age_recode9":"7","f_count":91,"m_count":133},{"birth_weight_recode12":"02","mother_bmi_recode":"3","mother_age_recode9":"8","f_count":18,"m_count":14},{"birth_weight_recode12":"02","mother_bmi_recode":"3","mother_age_recode9":"9","f_count":1,"m_count":1},{"birth_weight_recode12":"02","mother_bmi_recode":"4","mother_age_recode9":"1","f_count":2,"m_count":2},{"birth_weight_recode12":"02","mother_bmi_recode":"4","mother_age_recode9":"2","f_count":67,"m_count":80},{"birth_weight_recode12":"02","mother_bmi_recode":"4","mother_age_recode9":"3","f_count":303,"m_count":343},{"birth_weight_recode12":"02","mother_bmi_recode":"4","mother_age_recode9":"4","f_count":503,"m_count":479},{"birth_weight_recode12":"02","mother_bmi_recode":"4","mother_age_recode9":"5","f_count":465,"m_count":496},{"birth_weight_recode12":"02","mother_bmi_recode":"4","mother_age_recode9":"6","f_count":280,"m_count":275},{"birth_weight_recode12":"02","mother_bmi_recode":"4","mother_age_recode9":"7","f_count":88,"m_count":82},{"birth_weight_recode12":"02","mother_bmi_recode":"4","mother_age_recode9":"8","f_count":4,"m_count":8},{"birth_weight_recode12":"02","mother_bmi_recode":"4","mother_age_recode9":"9","f_count":3,"m_count":1},{"birth_weight_recode12":"02","mother_bmi_recode":"5","mother_age_recode9":"2","f_count":43,"m_count":35},{"birth_weight_recode12":"02","mother_bmi_recode":"5","mother_age_recode9":"3","f_count":170,"m_count":182},{"birth_weight_recode12":"02","mother_bmi_recode":"5","mother_age_recode9":"4","f_count":249,"m_count":272},{"birth_weight_recode12":"02","mother_bmi_recode":"5","mother_age_recode9":"5","f_count":280,"m_count":261},{"birth_weight_recode12":"02","mother_bmi_recode":"5","mother_age_recode9":"6","f_count":196,"m_count":171},{"birth_weight_recode12":"02","mother_bmi_recode":"5","mother_age_recode9":"7","f_count":42,"m_count":38},{"birth_weight_recode12":"02","mother_bmi_recode":"5","mother_age_recode9":"8","f_count":1,"m_count":3},{"birth_weight_recode12":"02","mother_bmi_recode":"6","mother_age_recode9":"2","f_count":17,"m_count":20},{"birth_weight_recode12":"02","mother_bmi_recode":"6","mother_age_recode9":"3","f_count":135,"m_count":155},{"birth_weight_recode12":"02","mother_bmi_recode":"6","mother_age_recode9":"4","f_count":221,"m_count":240},{"birth_weight_recode12":"02","mother_bmi_recode":"6","mother_age_recode9":"5","f_count":215,"m_count":208},{"birth_weight_recode12":"02","mother_bmi_recode":"6","mother_age_recode9":"6","f_count":136,"m_count":128},{"birth_weight_recode12":"02","mother_bmi_recode":"6","mother_age_recode9":"7","f_count":24,"m_count":28},{"birth_weight_recode12":"02","mother_bmi_recode":"6","mother_age_recode9":"8","f_count":3,"m_count":1},{"birth_weight_recode12":"02","mother_bmi_recode":"9","mother_age_recode9":"2","f_count":41,"m_count":48},{"birth_weight_recode12":"02","mother_bmi_recode":"9","mother_age_recode9":"3","f_count":105,"m_count":114},{"birth_weight_recode12":"02","mother_bmi_recode":"9","mother_age_recode9":"4","f_count":159,"m_count":175},{"birth_weight_recode12":"02","mother_bmi_recode":"9","mother_age_recode9":"5","f_count":143,"m_count":147},{"birth_weight_recode12":"02","mother_bmi_recode":"9","mother_age_recode9":"6","f_count":104,"m_count":118},{"birth_weight_recode12":"02","mother_bmi_recode":"9","mother_age_recode9":"7","f_count":25,"m_count":26},{"birth_weight_recode12":"03","mother_bmi_recode":"1","mother_age_recode9":"2","f_count":59,"m_count":78},{"birth_weight_recode12":"03","mother_bmi_recode":"1","mother_age_recode9":"3","f_count":184,"m_count":177},{"birth_weight_recode12":"03","mother_bmi_recode":"1","mother_age_recode9":"4","f_count":179,"m_count":158},{"birth_weight_recode12":"03","mother_bmi_recode":"1","mother_age_recode9":"5","f_count":90,"m_count":102},{"birth_weight_recode12":"03","mother_bmi_recode":"1","mother_age_recode9":"6","f_count":37,"m_count":46},{"birth_weight_recode12":"03","mother_bmi_recode":"1","mother_age_recode9":"7","f_count":11,"m_count":7},{"birth_weight_recode12":"03","mother_bmi_recode":"1","mother_age_recode9":"8","f_count":2,"m_count":1},{"birth_weight_recode12":"03","mother_bmi_recode":"2","mother_age_recode9":"1","f_count":6,"m_count":6},{"birth_weight_recode12":"03","mother_bmi_recode":"2","mother_age_recode9":"2","f_count":376,"m_count":423},{"birth_weight_recode12":"03","mother_bmi_recode":"2","mother_age_recode9":"3","f_count":1124,"m_count":1107},{"birth_weight_recode12":"03","mother_bmi_recode":"2","mother_age_recode9":"4","f_count":1323,"m_count":1300},{"birth_weight_recode12":"03","mother_bmi_recode":"2","mother_age_recode9":"5","f_count":1328,"m_count":1318},{"birth_weight_recode12":"03","mother_bmi_recode":"2","mother_age_recode9":"6","f_count":787,"m_count":758},{"birth_weight_recode12":"03","mother_bmi_recode":"2","mother_age_recode9":"7","f_count":214,"m_count":200},{"birth_weight_recode12":"03","mother_bmi_recode":"2","mother_age_recode9":"8","f_count":32,"m_count":36},{"birth_weight_recode12":"03","mother_bmi_recode":"2","mother_age_recode9":"9","f_count":6,"m_count":4},{"birth_weight_recode12":"03","mother_bmi_recode":"3","mother_age_recode9":"2","f_count":172,"m_count":173},{"birth_weight_recode12":"03","mother_bmi_recode":"3","mother_age_recode9":"3","f_count":631,"m_count":607},{"birth_weight_recode12":"03","mother_bmi_recode":"3","mother_age_recode9":"4","f_count":863,"m_count":866},{"birth_weight_recode12":"03","mother_bmi_recode":"3","mother_age_recode9":"5","f_count":861,"m_count":979},{"birth_weight_recode12":"03","mother_bmi_recode":"3","mother_age_recode9":"6","f_count":617,"m_count":602},{"birth_weight_recode12":"03","mother_bmi_recode":"3","mother_age_recode9":"7","f_count":156,"m_count":151},{"birth_weight_recode12":"03","mother_bmi_recode":"3","mother_age_recode9":"8","f_count":25,"m_count":31},{"birth_weight_recode12":"03","mother_bmi_recode":"3","mother_age_recode9":"9","f_count":3,"m_count":7},{"birth_weight_recode12":"03","mother_bmi_recode":"4","mother_age_recode9":"2","f_count":86,"m_count":89},{"birth_weight_recode12":"03","mother_bmi_recode":"4","mother_age_recode9":"3","f_count":358,"m_count":421},{"birth_weight_recode12":"03","mother_bmi_recode":"4","mother_age_recode9":"4","f_count":611,"m_count":632},{"birth_weight_recode12":"03","mother_bmi_recode":"4","mother_age_recode9":"5","f_count":638,"m_count":610},{"birth_weight_recode12":"03","mother_bmi_recode":"4","mother_age_recode9":"6","f_count":363,"m_count":427},{"birth_weight_recode12":"03","mother_bmi_recode":"4","mother_age_recode9":"7","f_count":116,"m_count":129},{"birth_weight_recode12":"03","mother_bmi_recode":"4","mother_age_recode9":"8","f_count":14,"m_count":13},{"birth_weight_recode12":"03","mother_bmi_recode":"4","mother_age_recode9":"9","f_count":2,"m_count":4},{"birth_weight_recode12":"03","mother_bmi_recode":"5","mother_age_recode9":"2","f_count":50,"m_count":32},{"birth_weight_recode12":"03","mother_bmi_recode":"5","mother_age_recode9":"3","f_count":246,"m_count":228},{"birth_weight_recode12":"03","mother_bmi_recode":"5","mother_age_recode9":"4","f_count":367,"m_count":356},{"birth_weight_recode12":"03","mother_bmi_recode":"5","mother_age_recode9":"5","f_count":364,"m_count":327},{"birth_weight_recode12":"03","mother_bmi_recode":"5","mother_age_recode9":"6","f_count":217,"m_count":227},{"birth_weight_recode12":"03","mother_bmi_recode":"5","mother_age_recode9":"7","f_count":58,"m_count":53},{"birth_weight_recode12":"03","mother_bmi_recode":"5","mother_age_recode9":"8","f_count":6,"m_count":11},{"birth_weight_recode12":"03","mother_bmi_recode":"6","mother_age_recode9":"2","f_count":24,"m_count":33},{"birth_weight_recode12":"03","mother_bmi_recode":"6","mother_age_recode9":"3","f_count":175,"m_count":179},{"birth_weight_recode12":"03","mother_bmi_recode":"6","mother_age_recode9":"4","f_count":271,"m_count":289},{"birth_weight_recode12":"03","mother_bmi_recode":"6","mother_age_recode9":"5","f_count":280,"m_count":294},{"birth_weight_recode12":"03","mother_bmi_recode":"6","mother_age_recode9":"6","f_count":163,"m_count":168},{"birth_weight_recode12":"03","mother_bmi_recode":"6","mother_age_recode9":"7","f_count":52,"m_count":50},{"birth_weight_recode12":"03","mother_bmi_recode":"6","mother_age_recode9":"8","f_count":4,"m_count":1},{"birth_weight_recode12":"03","mother_bmi_recode":"9","mother_age_recode9":"1","f_count":1,"m_count":1},{"birth_weight_recode12":"03","mother_bmi_recode":"9","mother_age_recode9":"2","f_count":34,"m_count":52},{"birth_weight_recode12":"03","mother_bmi_recode":"9","mother_age_recode9":"3","f_count":135,"m_count":139},{"birth_weight_recode12":"03","mother_bmi_recode":"9","mother_age_recode9":"4","f_count":177,"m_count":189},{"birth_weight_recode12":"03","mother_bmi_recode":"9","mother_age_recode9":"5","f_count":188,"m_count":184},{"birth_weight_recode12":"03","mother_bmi_recode":"9","mother_age_recode9":"6","f_count":126,"m_count":118},{"birth_weight_recode12":"03","mother_bmi_recode":"9","mother_age_recode9":"7","f_count":46,"m_count":40},{"birth_weight_recode12":"03","mother_bmi_recode":"9","mother_age_recode9":"8","f_count":5,"m_count":5},{"birth_weight_recode12":"04","mother_bmi_recode":"1","mother_age_recode9":"1","f_count":7,"m_count":3},{"birth_weight_recode12":"04","mother_bmi_recode":"1","mother_age_recode9":"2","f_count":178,"m_count":188},{"birth_weight_recode12":"04","mother_bmi_recode":"1","mother_age_recode9":"3","f_count":478,"m_count":386},{"birth_weight_recode12":"04","mother_bmi_recode":"1","mother_age_recode9":"4","f_count":399,"m_count":355},{"birth_weight_recode12":"04","mother_bmi_recode":"1","mother_age_recode9":"5","f_count":270,"m_count":246},{"birth_weight_recode12":"04","mother_bmi_recode":"1","mother_age_recode9":"6","f_count":130,"m_count":139},{"birth_weight_recode12":"04","mother_bmi_recode":"1","mother_age_recode9":"7","f_count":28,"m_count":25},{"birth_weight_recode12":"04","mother_bmi_recode":"2","mother_age_recode9":"1","f_count":7,"m_count":11},{"birth_weight_recode12":"04","mother_bmi_recode":"2","mother_age_recode9":"2","f_count":906,"m_count":838},{"birth_weight_recode12":"04","mother_bmi_recode":"2","mother_age_recode9":"3","f_count":2570,"m_count":2415},{"birth_weight_recode12":"04","mother_bmi_recode":"2","mother_age_recode9":"4","f_count":3401,"m_count":3116},{"birth_weight_recode12":"04","mother_bmi_recode":"2","mother_age_recode9":"5","f_count":3469,"m_count":3201},{"birth_weight_recode12":"04","mother_bmi_recode":"2","mother_age_recode9":"6","f_count":1919,"m_count":1879},{"birth_weight_recode12":"04","mother_bmi_recode":"2","mother_age_recode9":"7","f_count":502,"m_count":461},{"birth_weight_recode12":"04","mother_bmi_recode":"2","mother_age_recode9":"8","f_count":79,"m_count":73},{"birth_weight_recode12":"04","mother_bmi_recode":"2","mother_age_recode9":"9","f_count":24,"m_count":12},{"birth_weight_recode12":"04","mother_bmi_recode":"3","mother_age_recode9":"1","f_count":2,"m_count":3},{"birth_weight_recode12":"04","mother_bmi_recode":"3","mother_age_recode9":"2","f_count":359,"m_count":328},{"birth_weight_recode12":"04","mother_bmi_recode":"3","mother_age_recode9":"3","f_count":1353,"m_count":1306},{"birth_weight_recode12":"04","mother_bmi_recode":"3","mother_age_recode9":"4","f_count":1893,"m_count":1904},{"birth_weight_recode12":"04","mother_bmi_recode":"3","mother_age_recode9":"5","f_count":2144,"m_count":1976},{"birth_weight_recode12":"04","mother_bmi_recode":"3","mother_age_recode9":"6","f_count":1377,"m_count":1264},{"birth_weight_recode12":"04","mother_bmi_recode":"3","mother_age_recode9":"7","f_count":343,"m_count":380},{"birth_weight_recode12":"04","mother_bmi_recode":"3","mother_age_recode9":"8","f_count":53,"m_count":40},{"birth_weight_recode12":"04","mother_bmi_recode":"3","mother_age_recode9":"9","f_count":8,"m_count":4},{"birth_weight_recode12":"04","mother_bmi_recode":"4","mother_age_recode9":"2","f_count":201,"m_count":164},{"birth_weight_recode12":"04","mother_bmi_recode":"4","mother_age_recode9":"3","f_count":841,"m_count":811},{"birth_weight_recode12":"04","mother_bmi_recode":"4","mother_age_recode9":"4","f_count":1248,"m_count":1220},{"birth_weight_recode12":"04","mother_bmi_recode":"4","mother_age_recode9":"5","f_count":1225,"m_count":1290},{"birth_weight_recode12":"04","mother_bmi_recode":"4","mother_age_recode9":"6","f_count":870,"m_count":784},{"birth_weight_recode12":"04","mother_bmi_recode":"4","mother_age_recode9":"7","f_count":253,"m_count":211},{"birth_weight_recode12":"04","mother_bmi_recode":"4","mother_age_recode9":"8","f_count":36,"m_count":22},{"birth_weight_recode12":"04","mother_bmi_recode":"4","mother_age_recode9":"9","f_count":8,"m_count":4},{"birth_weight_recode12":"04","mother_bmi_recode":"5","mother_age_recode9":"1","f_count":1,"m_count":1},{"birth_weight_recode12":"04","mother_bmi_recode":"5","mother_age_recode9":"2","f_count":77,"m_count":63},{"birth_weight_recode12":"04","mother_bmi_recode":"5","mother_age_recode9":"3","f_count":437,"m_count":442},{"birth_weight_recode12":"04","mother_bmi_recode":"5","mother_age_recode9":"4","f_count":667,"m_count":686},{"birth_weight_recode12":"04","mother_bmi_recode":"5","mother_age_recode9":"5","f_count":712,"m_count":631},{"birth_weight_recode12":"04","mother_bmi_recode":"5","mother_age_recode9":"6","f_count":439,"m_count":407},{"birth_weight_recode12":"04","mother_bmi_recode":"5","mother_age_recode9":"7","f_count":142,"m_count":120},{"birth_weight_recode12":"04","mother_bmi_recode":"5","mother_age_recode9":"8","f_count":9,"m_count":9},{"birth_weight_recode12":"04","mother_bmi_recode":"6","mother_age_recode9":"2","f_count":46,"m_count":41},{"birth_weight_recode12":"04","mother_bmi_recode":"6","mother_age_recode9":"3","f_count":308,"m_count":308},{"birth_weight_recode12":"04","mother_bmi_recode":"6","mother_age_recode9":"4","f_count":599,"m_count":540},{"birth_weight_recode12":"04","mother_bmi_recode":"6","mother_age_recode9":"5","f_count":529,"m_count":466},{"birth_weight_recode12":"04","mother_bmi_recode":"6","mother_age_recode9":"6","f_count":341,"m_count":303},{"birth_weight_recode12":"04","mother_bmi_recode":"6","mother_age_recode9":"7","f_count":73,"m_count":87},{"birth_weight_recode12":"04","mother_bmi_recode":"6","mother_age_recode9":"8","f_count":8,"m_count":4},{"birth_weight_recode12":"04","mother_bmi_recode":"9","mother_age_recode9":"1","f_count":3,"m_count":3},{"birth_weight_recode12":"04","mother_bmi_recode":"9","mother_age_recode9":"2","f_count":94,"m_count":87},{"birth_weight_recode12":"04","mother_bmi_recode":"9","mother_age_recode9":"3","f_count":261,"m_count":284},{"birth_weight_recode12":"04","mother_bmi_recode":"9","mother_age_recode9":"4","f_count":311,"m_count":289},{"birth_weight_recode12":"04","mother_bmi_recode":"9","mother_age_recode9":"5","f_count":333,"m_count":331},{"birth_weight_recode12":"04","mother_bmi_recode":"9","mother_age_recode9":"6","f_count":217,"m_count":208},{"birth_weight_recode12":"04","mother_bmi_recode":"9","mother_age_recode9":"7","f_count":58,"m_count":55},{"birth_weight_recode12":"04","mother_bmi_recode":"9","mother_age_recode9":"8","f_count":8,"m_count":9},{"birth_weight_recode12":"04","mother_bmi_recode":"9","mother_age_recode9":"9","f_count":3,"m_count":2},{"birth_weight_recode12":"05","mother_bmi_recode":"1","mother_age_recode9":"1","f_count":7,"m_count":10},{"birth_weight_recode12":"05","mother_bmi_recode":"1","mother_age_recode9":"2","f_count":745,"m_count":632},{"birth_weight_recode12":"05","mother_bmi_recode":"1","mother_age_recode9":"3","f_count":2025,"m_count":1569},{"birth_weight_recode12":"05","mother_bmi_recode":"1","mother_age_recode9":"4","f_count":1677,"m_count":1327},{"birth_weight_recode12":"05","mother_bmi_recode":"1","mother_age_recode9":"5","f_count":1183,"m_count":925},{"birth_weight_recode12":"05","mother_bmi_recode":"1","mother_age_recode9":"6","f_count":524,"m_count":416},{"birth_weight_recode12":"05","mother_bmi_recode":"1","mother_age_recode9":"7","f_count":100,"m_count":85},{"birth_weight_recode12":"05","mother_bmi_recode":"1","mother_age_recode9":"8","f_count":13,"m_count":11},{"birth_weight_recode12":"05","mother_bmi_recode":"2","mother_age_recode9":"1","f_count":42,"m_count":31},{"birth_weight_recode12":"05","mother_bmi_recode":"2","mother_age_recode9":"2","f_count":3426,"m_count":2982},{"birth_weight_recode12":"05","mother_bmi_recode":"2","mother_age_recode9":"3","f_count":10452,"m_count":8442},{"birth_weight_recode12":"05","mother_bmi_recode":"2","mother_age_recode9":"4","f_count":12812,"m_count":10344},{"birth_weight_recode12":"05","mother_bmi_recode":"2","mother_age_recode9":"5","f_count":12547,"m_count":10434},{"birth_weight_recode12":"05","mother_bmi_recode":"2","mother_age_recode9":"6","f_count":6649,"m_count":5544},{"birth_weight_recode12":"05","mother_bmi_recode":"2","mother_age_recode9":"7","f_count":1605,"m_count":1278},{"birth_weight_recode12":"05","mother_bmi_recode":"2","mother_age_recode9":"8","f_count":185,"m_count":173},{"birth_weight_recode12":"05","mother_bmi_recode":"2","mother_age_recode9":"9","f_count":20,"m_count":28},{"birth_weight_recode12":"05","mother_bmi_recode":"3","mother_age_recode9":"1","f_count":9,"m_count":14},{"birth_weight_recode12":"05","mother_bmi_recode":"3","mother_age_recode9":"2","f_count":1190,"m_count":1069},{"birth_weight_recode12":"05","mother_bmi_recode":"3","mother_age_recode9":"3","f_count":4929,"m_count":4165},{"birth_weight_recode12":"05","mother_bmi_recode":"3","mother_age_recode9":"4","f_count":7109,"m_count":5874},{"birth_weight_recode12":"05","mother_bmi_recode":"3","mother_age_recode9":"5","f_count":7007,"m_count":5940},{"birth_weight_recode12":"05","mother_bmi_recode":"3","mother_age_recode9":"6","f_count":4102,"m_count":3617},{"birth_weight_recode12":"05","mother_bmi_recode":"3","mother_age_recode9":"7","f_count":1078,"m_count":936},{"birth_weight_recode12":"05","mother_bmi_recode":"3","mother_age_recode9":"8","f_count":138,"m_count":112},{"birth_weight_recode12":"05","mother_bmi_recode":"3","mother_age_recode9":"9","f_count":24,"m_count":12},{"birth_weight_recode12":"05","mother_bmi_recode":"4","mother_age_recode9":"1","f_count":3,"m_count":5},{"birth_weight_recode12":"05","mother_bmi_recode":"4","mother_age_recode9":"2","f_count":563,"m_count":524},{"birth_weight_recode12":"05","mother_bmi_recode":"4","mother_age_recode9":"3","f_count":2808,"m_count":2382},{"birth_weight_recode12":"05","mother_bmi_recode":"4","mother_age_recode9":"4","f_count":4125,"m_count":3493},{"birth_weight_recode12":"05","mother_bmi_recode":"4","mother_age_recode9":"5","f_count":3704,"m_count":3337},{"birth_weight_recode12":"05","mother_bmi_recode":"4","mother_age_recode9":"6","f_count":2367,"m_count":2060},{"birth_weight_recode12":"05","mother_bmi_recode":"4","mother_age_recode9":"7","f_count":689,"m_count":567},{"birth_weight_recode12":"05","mother_bmi_recode":"4","mother_age_recode9":"8","f_count":62,"m_count":59},{"birth_weight_recode12":"05","mother_bmi_recode":"4","mother_age_recode9":"9","f_count":14,"m_count":12},{"birth_weight_recode12":"05","mother_bmi_recode":"5","mother_age_recode9":"2","f_count":234,"m_count":201},{"birth_weight_recode12":"05","mother_bmi_recode":"5","mother_age_recode9":"3","f_count":1360,"m_count":1214},{"birth_weight_recode12":"05","mother_bmi_recode":"5","mother_age_recode9":"4","f_count":2189,"m_count":1887},{"birth_weight_recode12":"05","mother_bmi_recode":"5","mother_age_recode9":"5","f_count":1936,"m_count":1645},{"birth_weight_recode12":"05","mother_bmi_recode":"5","mother_age_recode9":"6","f_count":1185,"m_count":1009},{"birth_weight_recode12":"05","mother_bmi_recode":"5","mother_age_recode9":"7","f_count":320,"m_count":295},{"birth_weight_recode12":"05","mother_bmi_recode":"5","mother_age_recode9":"8","f_count":25,"m_count":25},{"birth_weight_recode12":"05","mother_bmi_recode":"5","mother_age_recode9":"9","f_count":3,"m_count":2},{"birth_weight_recode12":"05","mother_bmi_recode":"6","mother_age_recode9":"2","f_count":143,"m_count":143},{"birth_weight_recode12":"05","mother_bmi_recode":"6","mother_age_recode9":"3","f_count":1026,"m_count":887},{"birth_weight_recode12":"05","mother_bmi_recode":"6","mother_age_recode9":"4","f_count":1724,"m_count":1503},{"birth_weight_recode12":"05","mother_bmi_recode":"6","mother_age_recode9":"5","f_count":1431,"m_count":1260},{"birth_weight_recode12":"05","mother_bmi_recode":"6","mother_age_recode9":"6","f_count":884,"m_count":724},{"birth_weight_recode12":"05","mother_bmi_recode":"6","mother_age_recode9":"7","f_count":187,"m_count":198},{"birth_weight_recode12":"05","mother_bmi_recode":"6","mother_age_recode9":"8","f_count":18,"m_count":13},{"birth_weight_recode12":"05","mother_bmi_recode":"6","mother_age_recode9":"9","f_count":2,"m_count":1},{"birth_weight_recode12":"05","mother_bmi_recode":"9","mother_age_recode9":"1","f_count":5,"m_count":9},{"birth_weight_recode12":"05","mother_bmi_recode":"9","mother_age_recode9":"2","f_count":221,"m_count":172},{"birth_weight_recode12":"05","mother_bmi_recode":"9","mother_age_recode9":"3","f_count":724,"m_count":609},{"birth_weight_recode12":"05","mother_bmi_recode":"9","mother_age_recode9":"4","f_count":892,"m_count":862},{"birth_weight_recode12":"05","mother_bmi_recode":"9","mother_age_recode9":"5","f_count":841,"m_count":816},{"birth_weight_recode12":"05","mother_bmi_recode":"9","mother_age_recode9":"6","f_count":594,"m_count":476},{"birth_weight_recode12":"05","mother_bmi_recode":"9","mother_age_recode9":"7","f_count":130,"m_count":125},{"birth_weight_recode12":"05","mother_bmi_recode":"9","mother_age_recode9":"8","f_count":15,"m_count":19},{"birth_weight_recode12":"05","mother_bmi_recode":"9","mother_age_recode9":"9","f_count":3,"m_count":2},{"birth_weight_recode12":"06","mother_bmi_recode":"1","mother_age_recode9":"1","f_count":26,"m_count":21},{"birth_weight_recode12":"06","mother_bmi_recode":"1","mother_age_recode9":"2","f_count":2266,"m_count":1917},{"birth_weight_recode12":"06","mother_bmi_recode":"1","mother_age_recode9":"3","f_count":5986,"m_count":5038},{"birth_weight_recode12":"06","mother_bmi_recode":"1","mother_age_recode9":"4","f_count":5426,"m_count":4517},{"birth_weight_recode12":"06","mother_bmi_recode":"1","mother_age_recode9":"5","f_count":3922,"m_count":3174},{"birth_weight_recode12":"06","mother_bmi_recode":"1","mother_age_recode9":"6","f_count":1708,"m_count":1376},{"birth_weight_recode12":"06","mother_bmi_recode":"1","mother_age_recode9":"7","f_count":305,"m_count":261},{"birth_weight_recode12":"06","mother_bmi_recode":"1","mother_age_recode9":"8","f_count":20,"m_count":21},{"birth_weight_recode12":"06","mother_bmi_recode":"2","mother_age_recode9":"1","f_count":167,"m_count":149},{"birth_weight_recode12":"06","mother_bmi_recode":"2","mother_age_recode9":"2","f_count":13297,"m_count":10922},{"birth_weight_recode12":"06","mother_bmi_recode":"2","mother_age_recode9":"3","f_count":40057,"m_count":31817},{"birth_weight_recode12":"06","mother_bmi_recode":"2","mother_age_recode9":"4","f_count":51278,"m_count":39605},{"birth_weight_recode12":"06","mother_bmi_recode":"2","mother_age_recode9":"5","f_count":48889,"m_count":37825},{"birth_weight_recode12":"06","mother_bmi_recode":"2","mother_age_recode9":"6","f_count":24306,"m_count":19045},{"birth_weight_recode12":"06","mother_bmi_recode":"2","mother_age_recode9":"7","f_count":5028,"m_count":3976},{"birth_weight_recode12":"06","mother_bmi_recode":"2","mother_age_recode9":"8","f_count":435,"m_count":387},{"birth_weight_recode12":"06","mother_bmi_recode":"2","mother_age_recode9":"9","f_count":40,"m_count":42},{"birth_weight_recode12":"06","mother_bmi_recode":"3","mother_age_recode9":"1","f_count":46,"m_count":46},{"birth_weight_recode12":"06","mother_bmi_recode":"3","mother_age_recode9":"2","f_count":5171,"m_count":4295},{"birth_weight_recode12":"06","mother_bmi_recode":"3","mother_age_recode9":"3","f_count":20410,"m_count":16017},{"birth_weight_recode12":"06","mother_bmi_recode":"3","mother_age_recode9":"4","f_count":27521,"m_count":21468},{"birth_weight_recode12":"06","mother_bmi_recode":"3","mother_age_recode9":"5","f_count":25102,"m_count":20243},{"birth_weight_recode12":"06","mother_bmi_recode":"3","mother_age_recode9":"6","f_count":13602,"m_count":11379},{"birth_weight_recode12":"06","mother_bmi_recode":"3","mother_age_recode9":"7","f_count":3299,"m_count":2714},{"birth_weight_recode12":"06","mother_bmi_recode":"3","mother_age_recode9":"8","f_count":269,"m_count":264},{"birth_weight_recode12":"06","mother_bmi_recode":"3","mother_age_recode9":"9","f_count":28,"m_count":24},{"birth_weight_recode12":"06","mother_bmi_recode":"4","mother_age_recode9":"1","f_count":14,"m_count":12},{"birth_weight_recode12":"06","mother_bmi_recode":"4","mother_age_recode9":"2","f_count":2389,"m_count":1941},{"birth_weight_recode12":"06","mother_bmi_recode":"4","mother_age_recode9":"3","f_count":11206,"m_count":8973},{"birth_weight_recode12":"06","mother_bmi_recode":"4","mother_age_recode9":"4","f_count":15437,"m_count":12121},{"birth_weight_recode12":"06","mother_bmi_recode":"4","mother_age_recode9":"5","f_count":13099,"m_count":10653},{"birth_weight_recode12":"06","mother_bmi_recode":"4","mother_age_recode9":"6","f_count":7297,"m_count":5977},{"birth_weight_recode12":"06","mother_bmi_recode":"4","mother_age_recode9":"7","f_count":1813,"m_count":1426},{"birth_weight_recode12":"06","mother_bmi_recode":"4","mother_age_recode9":"8","f_count":137,"m_count":140},{"birth_weight_recode12":"06","mother_bmi_recode":"4","mother_age_recode9":"9","f_count":15,"m_count":17},{"birth_weight_recode12":"06","mother_bmi_recode":"5","mother_age_recode9":"2","f_count":931,"m_count":823},{"birth_weight_recode12":"06","mother_bmi_recode":"5","mother_age_recode9":"3","f_count":5385,"m_count":4287},{"birth_weight_recode12":"06","mother_bmi_recode":"5","mother_age_recode9":"4","f_count":7573,"m_count":6041},{"birth_weight_recode12":"06","mother_bmi_recode":"5","mother_age_recode9":"5","f_count":6103,"m_count":5096},{"birth_weight_recode12":"06","mother_bmi_recode":"5","mother_age_recode9":"6","f_count":3419,"m_count":2888},{"birth_weight_recode12":"06","mother_bmi_recode":"5","mother_age_recode9":"7","f_count":847,"m_count":719},{"birth_weight_recode12":"06","mother_bmi_recode":"5","mother_age_recode9":"8","f_count":54,"m_count":37},{"birth_weight_recode12":"06","mother_bmi_recode":"5","mother_age_recode9":"9","f_count":5,"m_count":6},{"birth_weight_recode12":"06","mother_bmi_recode":"6","mother_age_recode9":"1","f_count":2,"m_count":1},{"birth_weight_recode12":"06","mother_bmi_recode":"6","mother_age_recode9":"2","f_count":472,"m_count":403},{"birth_weight_recode12":"06","mother_bmi_recode":"6","mother_age_recode9":"3","f_count":3685,"m_count":3041},{"birth_weight_recode12":"06","mother_bmi_recode":"6","mother_age_recode9":"4","f_count":5673,"m_count":4528},{"birth_weight_recode12":"06","mother_bmi_recode":"6","mother_age_recode9":"5","f_count":4376,"m_count":3695},{"birth_weight_recode12":"06","mother_bmi_recode":"6","mother_age_recode9":"6","f_count":2429,"m_count":2024},{"birth_weight_recode12":"06","mother_bmi_recode":"6","mother_age_recode9":"7","f_count":530,"m_count":437},{"birth_weight_recode12":"06","mother_bmi_recode":"6","mother_age_recode9":"8","f_count":33,"m_count":21},{"birth_weight_recode12":"06","mother_bmi_recode":"9","mother_age_recode9":"1","f_count":10,"m_count":16},{"birth_weight_recode12":"06","mother_bmi_recode":"9","mother_age_recode9":"2","f_count":727,"m_count":666},{"birth_weight_recode12":"06","mother_bmi_recode":"9","mother_age_recode9":"3","f_count":2376,"m_count":1923},{"birth_weight_recode12":"06","mother_bmi_recode":"9","mother_age_recode9":"4","f_count":3020,"m_count":2471},{"birth_weight_recode12":"06","mother_bmi_recode":"9","mother_age_recode9":"5","f_count":2726,"m_count":2211},{"birth_weight_recode12":"06","mother_bmi_recode":"9","mother_age_recode9":"6","f_count":1454,"m_count":1290},{"birth_weight_recode12":"06","mother_bmi_recode":"9","mother_age_recode9":"7","f_count":333,"m_count":316},{"birth_weight_recode12":"06","mother_bmi_recode":"9","mother_age_recode9":"8","f_count":32,"m_count":37},{"birth_weight_recode12":"06","mother_bmi_recode":"9","mother_age_recode9":"9","f_count":7,"m_count":1},{"birth_weight_recode12":"07","mother_bmi_recode":"1","mother_age_recode9":"1","f_count":32,"m_count":27},{"birth_weight_recode12":"07","mother_bmi_recode":"1","mother_age_recode9":"2","f_count":2552,"m_count":2690},{"birth_weight_recode12":"07","mother_bmi_recode":"1","mother_age_recode9":"3","f_count":6790,"m_count":7504},{"birth_weight_recode12":"07","mother_bmi_recode":"1","mother_age_recode9":"4","f_count":6888,"m_count":7486},{"birth_weight_recode12":"07","mother_bmi_recode":"1","mother_age_recode9":"5","f_count":5499,"m_count":5803},{"birth_weight_recode12":"07","mother_bmi_recode":"1","mother_age_recode9":"6","f_count":2225,"m_count":2366},{"birth_weight_recode12":"07","mother_bmi_recode":"1","mother_age_recode9":"7","f_count":374,"m_count":413},{"birth_weight_recode12":"07","mother_bmi_recode":"1","mother_age_recode9":"8","f_count":34,"m_count":30},{"birth_weight_recode12":"07","mother_bmi_recode":"1","mother_age_recode9":"9","f_count":1,"m_count":3},{"birth_weight_recode12":"07","mother_bmi_recode":"2","mother_age_recode9":"1","f_count":204,"m_count":208},{"birth_weight_recode12":"07","mother_bmi_recode":"2","mother_age_recode9":"2","f_count":19467,"m_count":20291},{"birth_weight_recode12":"07","mother_bmi_recode":"2","mother_age_recode9":"3","f_count":65846,"m_count":66390},{"birth_weight_recode12":"07","mother_bmi_recode":"2","mother_age_recode9":"4","f_count":95776,"m_count":93191},{"birth_weight_recode12":"07","mother_bmi_recode":"2","mother_age_recode9":"5","f_count":98485,"m_count":93257},{"birth_weight_recode12":"07","mother_bmi_recode":"2","mother_age_recode9":"6","f_count":46864,"m_count":44436},{"birth_weight_recode12":"07","mother_bmi_recode":"2","mother_age_recode9":"7","f_count":8891,"m_count":8423},{"birth_weight_recode12":"07","mother_bmi_recode":"2","mother_age_recode9":"8","f_count":621,"m_count":619},{"birth_weight_recode12":"07","mother_bmi_recode":"2","mother_age_recode9":"9","f_count":46,"m_count":57},{"birth_weight_recode12":"07","mother_bmi_recode":"3","mother_age_recode9":"1","f_count":99,"m_count":95},{"birth_weight_recode12":"07","mother_bmi_recode":"3","mother_age_recode9":"2","f_count":9333,"m_count":9171},{"birth_weight_recode12":"07","mother_bmi_recode":"3","mother_age_recode9":"3","f_count":38688,"m_count":37696},{"birth_weight_recode12":"07","mother_bmi_recode":"3","mother_age_recode9":"4","f_count":58190,"m_count":54748},{"birth_weight_recode12":"07","mother_bmi_recode":"3","mother_age_recode9":"5","f_count":55372,"m_count":50717},{"birth_weight_recode12":"07","mother_bmi_recode":"3","mother_age_recode9":"6","f_count":28183,"m_count":26166},{"birth_weight_recode12":"07","mother_bmi_recode":"3","mother_age_recode9":"7","f_count":6100,"m_count":5657},{"birth_weight_recode12":"07","mother_bmi_recode":"3","mother_age_recode9":"8","f_count":451,"m_count":384},{"birth_weight_recode12":"07","mother_bmi_recode":"3","mother_age_recode9":"9","f_count":48,"m_count":40},{"birth_weight_recode12":"07","mother_bmi_recode":"4","mother_age_recode9":"1","f_count":23,"m_count":35},{"birth_weight_recode12":"07","mother_bmi_recode":"4","mother_age_recode9":"2","f_count":4507,"m_count":4358},{"birth_weight_recode12":"07","mother_bmi_recode":"4","mother_age_recode9":"3","f_count":22359,"m_count":21616},{"birth_weight_recode12":"07","mother_bmi_recode":"4","mother_age_recode9":"4","f_count":32069,"m_count":30182},{"birth_weight_recode12":"07","mother_bmi_recode":"4","mother_age_recode9":"5","f_count":28123,"m_count":26110},{"birth_weight_recode12":"07","mother_bmi_recode":"4","mother_age_recode9":"6","f_count":14545,"m_count":13541},{"birth_weight_recode12":"07","mother_bmi_recode":"4","mother_age_recode9":"7","f_count":3241,"m_count":3003},{"birth_weight_recode12":"07","mother_bmi_recode":"4","mother_age_recode9":"8","f_count":201,"m_count":211},{"birth_weight_recode12":"07","mother_bmi_recode":"4","mother_age_recode9":"9","f_count":17,"m_count":19},{"birth_weight_recode12":"07","mother_bmi_recode":"5","mother_age_recode9":"1","f_count":11,"m_count":8},{"birth_weight_recode12":"07","mother_bmi_recode":"5","mother_age_recode9":"2","f_count":1882,"m_count":1799},{"birth_weight_recode12":"07","mother_bmi_recode":"5","mother_age_recode9":"3","f_count":10963,"m_count":10378},{"birth_weight_recode12":"07","mother_bmi_recode":"5","mother_age_recode9":"4","f_count":15868,"m_count":14878},{"birth_weight_recode12":"07","mother_bmi_recode":"5","mother_age_recode9":"5","f_count":13036,"m_count":12076},{"birth_weight_recode12":"07","mother_bmi_recode":"5","mother_age_recode9":"6","f_count":6444,"m_count":6204},{"birth_weight_recode12":"07","mother_bmi_recode":"5","mother_age_recode9":"7","f_count":1436,"m_count":1345},{"birth_weight_recode12":"07","mother_bmi_recode":"5","mother_age_recode9":"8","f_count":80,"m_count":74},{"birth_weight_recode12":"07","mother_bmi_recode":"5","mother_age_recode9":"9","f_count":9,"m_count":11},{"birth_weight_recode12":"07","mother_bmi_recode":"6","mother_age_recode9":"1","f_count":2,"m_count":3},{"birth_weight_recode12":"07","mother_bmi_recode":"6","mother_age_recode9":"2","f_count":990,"m_count":987},{"birth_weight_recode12":"07","mother_bmi_recode":"6","mother_age_recode9":"3","f_count":7171,"m_count":6948},{"birth_weight_recode12":"07","mother_bmi_recode":"6","mother_age_recode9":"4","f_count":11132,"m_count":10595},{"birth_weight_recode12":"07","mother_bmi_recode":"6","mother_age_recode9":"5","f_count":9086,"m_count":8622},{"birth_weight_recode12":"07","mother_bmi_recode":"6","mother_age_recode9":"6","f_count":4501,"m_count":4347},{"birth_weight_recode12":"07","mother_bmi_recode":"6","mother_age_recode9":"7","f_count":943,"m_count":822},{"birth_weight_recode12":"07","mother_bmi_recode":"6","mother_age_recode9":"8","f_count":43,"m_count":36},{"birth_weight_recode12":"07","mother_bmi_recode":"6","mother_age_recode9":"9","f_count":1,"m_count":1},{"birth_weight_recode12":"07","mother_bmi_recode":"9","mother_age_recode9":"1","f_count":21,"m_count":25},{"birth_weight_recode12":"07","mother_bmi_recode":"9","mother_age_recode9":"2","f_count":997,"m_count":1064},{"birth_weight_recode12":"07","mother_bmi_recode":"9","mother_age_recode9":"3","f_count":3682,"m_count":3800},{"birth_weight_recode12":"07","mother_bmi_recode":"9","mother_age_recode9":"4","f_count":4992,"m_count":4932},{"birth_weight_recode12":"07","mother_bmi_recode":"9","mother_age_recode9":"5","f_count":4842,"m_count":4622},{"birth_weight_recode12":"07","mother_bmi_recode":"9","mother_age_recode9":"6","f_count":2651,"m_count":2407},{"birth_weight_recode12":"07","mother_bmi_recode":"9","mother_age_recode9":"7","f_count":583,"m_count":563},{"birth_weight_recode12":"07","mother_bmi_recode":"9","mother_age_recode9":"8","f_count":37,"m_count":48},{"birth_weight_recode12":"07","mother_bmi_recode":"9","mother_age_recode9":"9","f_count":3,"m_count":5},{"birth_weight_recode12":"08","mother_bmi_recode":"1","mother_age_recode9":"1","f_count":10,"m_count":14},{"birth_weight_recode12":"08","mother_bmi_recode":"1","mother_age_recode9":"2","f_count":789,"m_count":1134},{"birth_weight_recode12":"08","mother_bmi_recode":"1","mother_age_recode9":"3","f_count":2093,"m_count":3231},{"birth_weight_recode12":"08","mother_bmi_recode":"1","mother_age_recode9":"4","f_count":2371,"m_count":3622},{"birth_weight_recode12":"08","mother_bmi_recode":"1","mother_age_recode9":"5","f_count":2075,"m_count":3069},{"birth_weight_recode12":"08","mother_bmi_recode":"1","mother_age_recode9":"6","f_count":847,"m_count":1294},{"birth_weight_recode12":"08","mother_bmi_recode":"1","mother_age_recode9":"7","f_count":157,"m_count":215},{"birth_weight_recode12":"08","mother_bmi_recode":"1","mother_age_recode9":"8","f_count":9,"m_count":9},{"birth_weight_recode12":"08","mother_bmi_recode":"1","mother_age_recode9":"9","f_count":2,"m_count":1},{"birth_weight_recode12":"08","mother_bmi_recode":"2","mother_age_recode9":"1","f_count":66,"m_count":97},{"birth_weight_recode12":"08","mother_bmi_recode":"2","mother_age_recode9":"2","f_count":7695,"m_count":10615},{"birth_weight_recode12":"08","mother_bmi_recode":"2","mother_age_recode9":"3","f_count":28976,"m_count":41279},{"birth_weight_recode12":"08","mother_bmi_recode":"2","mother_age_recode9":"4","f_count":49582,"m_count":68269},{"birth_weight_recode12":"08","mother_bmi_recode":"2","mother_age_recode9":"5","f_count":56009,"m_count":74767},{"birth_weight_recode12":"08","mother_bmi_recode":"2","mother_age_recode9":"6","f_count":26821,"m_count":35767},{"birth_weight_recode12":"08","mother_bmi_recode":"2","mother_age_recode9":"7","f_count":4660,"m_count":6304},{"birth_weight_recode12":"08","mother_bmi_recode":"2","mother_age_recode9":"8","f_count":287,"m_count":394},{"birth_weight_recode12":"08","mother_bmi_recode":"2","mother_age_recode9":"9","f_count":20,"m_count":36},{"birth_weight_recode12":"08","mother_bmi_recode":"3","mother_age_recode9":"1","f_count":24,"m_count":49},{"birth_weight_recode12":"08","mother_bmi_recode":"3","mother_age_recode9":"2","f_count":4318,"m_count":5975},{"birth_weight_recode12":"08","mother_bmi_recode":"3","mother_age_recode9":"3","f_count":20831,"m_count":28038},{"birth_weight_recode12":"08","mother_bmi_recode":"3","mother_age_recode9":"4","f_count":35790,"m_count":46381},{"birth_weight_recode12":"08","mother_bmi_recode":"3","mother_age_recode9":"5","f_count":37482,"m_count":46617},{"birth_weight_recode12":"08","mother_bmi_recode":"3","mother_age_recode9":"6","f_count":18868,"m_count":23323},{"birth_weight_recode12":"08","mother_bmi_recode":"3","mother_age_recode9":"7","f_count":3813,"m_count":4659},{"birth_weight_recode12":"08","mother_bmi_recode":"3","mother_age_recode9":"8","f_count":225,"m_count":293},{"birth_weight_recode12":"08","mother_bmi_recode":"3","mother_age_recode9":"9","f_count":21,"m_count":17},{"birth_weight_recode12":"08","mother_bmi_recode":"4","mother_age_recode9":"1","f_count":20,"m_count":22},{"birth_weight_recode12":"08","mother_bmi_recode":"4","mother_age_recode9":"2","f_count":2418,"m_count":3177},{"birth_weight_recode12":"08","mother_bmi_recode":"4","mother_age_recode9":"3","f_count":13282,"m_count":17003},{"birth_weight_recode12":"08","mother_bmi_recode":"4","mother_age_recode9":"4","f_count":21206,"m_count":26847},{"birth_weight_recode12":"08","mother_bmi_recode":"4","mother_age_recode9":"5","f_count":20250,"m_count":24786},{"birth_weight_recode12":"08","mother_bmi_recode":"4","mother_age_recode9":"6","f_count":10637,"m_count":12823},{"birth_weight_recode12":"08","mother_bmi_recode":"4","mother_age_recode9":"7","f_count":2224,"m_count":2643},{"birth_weight_recode12":"08","mother_bmi_recode":"4","mother_age_recode9":"8","f_count":106,"m_count":162},{"birth_weight_recode12":"08","mother_bmi_recode":"4","mother_age_recode9":"9","f_count":7,"m_count":18},{"birth_weight_recode12":"08","mother_bmi_recode":"5","mother_age_recode9":"1","f_count":4,"m_count":5},{"birth_weight_recode12":"08","mother_bmi_recode":"5","mother_age_recode9":"2","f_count":1061,"m_count":1399},{"birth_weight_recode12":"08","mother_bmi_recode":"5","mother_age_recode9":"3","f_count":6709,"m_count":8514},{"birth_weight_recode12":"08","mother_bmi_recode":"5","mother_age_recode9":"4","f_count":11012,"m_count":13582},{"birth_weight_recode12":"08","mother_bmi_recode":"5","mother_age_recode9":"5","f_count":9861,"m_count":11877},{"birth_weight_recode12":"08","mother_bmi_recode":"5","mother_age_recode9":"6","f_count":5241,"m_count":5825},{"birth_weight_recode12":"08","mother_bmi_recode":"5","mother_age_recode9":"7","f_count":982,"m_count":1248},{"birth_weight_recode12":"08","mother_bmi_recode":"5","mother_age_recode9":"8","f_count":54,"m_count":61},{"birth_weight_recode12":"08","mother_bmi_recode":"5","mother_age_recode9":"9","f_count":2,"m_count":5},{"birth_weight_recode12":"08","mother_bmi_recode":"6","mother_age_recode9":"1","f_count":1,"m_count":2},{"birth_weight_recode12":"08","mother_bmi_recode":"6","mother_age_recode9":"2","f_count":567,"m_count":720},{"birth_weight_recode12":"08","mother_bmi_recode":"6","mother_age_recode9":"3","f_count":4677,"m_count":5804},{"birth_weight_recode12":"08","mother_bmi_recode":"6","mother_age_recode9":"4","f_count":8162,"m_count":9828},{"birth_weight_recode12":"08","mother_bmi_recode":"6","mother_age_recode9":"5","f_count":7064,"m_count":8110},{"birth_weight_recode12":"08","mother_bmi_recode":"6","mother_age_recode9":"6","f_count":3604,"m_count":4132},{"birth_weight_recode12":"08","mother_bmi_recode":"6","mother_age_recode9":"7","f_count":657,"m_count":769},{"birth_weight_recode12":"08","mother_bmi_recode":"6","mother_age_recode9":"8","f_count":32,"m_count":38},{"birth_weight_recode12":"08","mother_bmi_recode":"9","mother_age_recode9":"1","f_count":6,"m_count":6},{"birth_weight_recode12":"08","mother_bmi_recode":"9","mother_age_recode9":"2","f_count":401,"m_count":553},{"birth_weight_recode12":"08","mother_bmi_recode":"9","mother_age_recode9":"3","f_count":1674,"m_count":2361},{"birth_weight_recode12":"08","mother_bmi_recode":"9","mother_age_recode9":"4","f_count":2741,"m_count":3610},{"birth_weight_recode12":"08","mother_bmi_recode":"9","mother_age_recode9":"5","f_count":2951,"m_count":3669},{"birth_weight_recode12":"08","mother_bmi_recode":"9","mother_age_recode9":"6","f_count":1584,"m_count":2000},{"birth_weight_recode12":"08","mother_bmi_recode":"9","mother_age_recode9":"7","f_count":331,"m_count":426},{"birth_weight_recode12":"08","mother_bmi_recode":"9","mother_age_recode9":"8","f_count":13,"m_count":29},{"birth_weight_recode12":"08","mother_bmi_recode":"9","mother_age_recode9":"9","f_count":1,"m_count":1},{"birth_weight_recode12":"09","mother_bmi_recode":"1","mother_age_recode9":"1","f_count":1,"m_count":2},{"birth_weight_recode12":"09","mother_bmi_recode":"1","mother_age_recode9":"2","f_count":58,"m_count":151},{"birth_weight_recode12":"09","mother_bmi_recode":"1","mother_age_recode9":"3","f_count":221,"m_count":525},{"birth_weight_recode12":"09","mother_bmi_recode":"1","mother_age_recode9":"4","f_count":266,"m_count":647},{"birth_weight_recode12":"09","mother_bmi_recode":"1","mother_age_recode9":"5","f_count":266,"m_count":590},{"birth_weight_recode12":"09","mother_bmi_recode":"1","mother_age_recode9":"6","f_count":102,"m_count":251},{"birth_weight_recode12":"09","mother_bmi_recode":"1","mother_age_recode9":"7","f_count":19,"m_count":42},{"birth_weight_recode12":"09","mother_bmi_recode":"2","mother_age_recode9":"1","f_count":9,"m_count":17},{"birth_weight_recode12":"09","mother_bmi_recode":"2","mother_age_recode9":"2","f_count":1013,"m_count":1975},{"birth_weight_recode12":"09","mother_bmi_recode":"2","mother_age_recode9":"3","f_count":4301,"m_count":8534},{"birth_weight_recode12":"09","mother_bmi_recode":"2","mother_age_recode9":"4","f_count":8388,"m_count":16682},{"birth_weight_recode12":"09","mother_bmi_recode":"2","mother_age_recode9":"5","f_count":10469,"m_count":19885},{"birth_weight_recode12":"09","mother_bmi_recode":"2","mother_age_recode9":"6","f_count":5171,"m_count":9877},{"birth_weight_recode12":"09","mother_bmi_recode":"2","mother_age_recode9":"7","f_count":849,"m_count":1706},{"birth_weight_recode12":"09","mother_bmi_recode":"2","mother_age_recode9":"8","f_count":59,"m_count":119},{"birth_weight_recode12":"09","mother_bmi_recode":"2","mother_age_recode9":"9","f_count":3,"m_count":7},{"birth_weight_recode12":"09","mother_bmi_recode":"3","mother_age_recode9":"1","f_count":2,"m_count":9},{"birth_weight_recode12":"09","mother_bmi_recode":"3","mother_age_recode9":"2","f_count":717,"m_count":1265},{"birth_weight_recode12":"09","mother_bmi_recode":"3","mother_age_recode9":"3","f_count":3748,"m_count":6944},{"birth_weight_recode12":"09","mother_bmi_recode":"3","mother_age_recode9":"4","f_count":7759,"m_count":13610},{"birth_weight_recode12":"09","mother_bmi_recode":"3","mother_age_recode9":"5","f_count":8775,"m_count":15418},{"birth_weight_recode12":"09","mother_bmi_recode":"3","mother_age_recode9":"6","f_count":4592,"m_count":7714},{"birth_weight_recode12":"09","mother_bmi_recode":"3","mother_age_recode9":"7","f_count":888,"m_count":1496},{"birth_weight_recode12":"09","mother_bmi_recode":"3","mother_age_recode9":"8","f_count":50,"m_count":83},{"birth_weight_recode12":"09","mother_bmi_recode":"3","mother_age_recode9":"9","f_count":3,"m_count":7},{"birth_weight_recode12":"09","mother_bmi_recode":"4","mother_age_recode9":"1","f_count":4,"m_count":3},{"birth_weight_recode12":"09","mother_bmi_recode":"4","mother_age_recode9":"2","f_count":465,"m_count":755},{"birth_weight_recode12":"09","mother_bmi_recode":"4","mother_age_recode9":"3","f_count":2745,"m_count":4701},{"birth_weight_recode12":"09","mother_bmi_recode":"4","mother_age_recode9":"4","f_count":5231,"m_count":8549},{"birth_weight_recode12":"09","mother_bmi_recode":"4","mother_age_recode9":"5","f_count":5426,"m_count":8897},{"birth_weight_recode12":"09","mother_bmi_recode":"4","mother_age_recode9":"6","f_count":2968,"m_count":4720},{"birth_weight_recode12":"09","mother_bmi_recode":"4","mother_age_recode9":"7","f_count":614,"m_count":880},{"birth_weight_recode12":"09","mother_bmi_recode":"4","mother_age_recode9":"8","f_count":30,"m_count":64},{"birth_weight_recode12":"09","mother_bmi_recode":"4","mother_age_recode9":"9","f_count":2,"m_count":7},{"birth_weight_recode12":"09","mother_bmi_recode":"5","mother_age_recode9":"2","f_count":189,"m_count":358},{"birth_weight_recode12":"09","mother_bmi_recode":"5","mother_age_recode9":"3","f_count":1548,"m_count":2634},{"birth_weight_recode12":"09","mother_bmi_recode":"5","mother_age_recode9":"4","f_count":2862,"m_count":4614},{"birth_weight_recode12":"09","mother_bmi_recode":"5","mother_age_recode9":"5","f_count":2901,"m_count":4582},{"birth_weight_recode12":"09","mother_bmi_recode":"5","mother_age_recode9":"6","f_count":1563,"m_count":2298},{"birth_weight_recode12":"09","mother_bmi_recode":"5","mother_age_recode9":"7","f_count":321,"m_count":491},{"birth_weight_recode12":"09","mother_bmi_recode":"5","mother_age_recode9":"8","f_count":17,"m_count":19},{"birth_weight_recode12":"09","mother_bmi_recode":"5","mother_age_recode9":"9","f_count":1,"m_count":1},{"birth_weight_recode12":"09","mother_bmi_recode":"6","mother_age_recode9":"2","f_count":121,"m_count":194},{"birth_weight_recode12":"09","mother_bmi_recode":"6","mother_age_recode9":"3","f_count":1162,"m_count":1967},{"birth_weight_recode12":"09","mother_bmi_recode":"6","mother_age_recode9":"4","f_count":2389,"m_count":3640},{"birth_weight_recode12":"09","mother_bmi_recode":"6","mother_age_recode9":"5","f_count":2500,"m_count":3361},{"birth_weight_recode12":"09","mother_bmi_recode":"6","mother_age_recode9":"6","f_count":1251,"m_count":1762},{"birth_weight_recode12":"09","mother_bmi_recode":"6","mother_age_recode9":"7","f_count":216,"m_count":307},{"birth_weight_recode12":"09","mother_bmi_recode":"6","mother_age_recode9":"8","f_count":13,"m_count":12},{"birth_weight_recode12":"09","mother_bmi_recode":"9","mother_age_recode9":"1","f_count":1,"m_count":2},{"birth_weight_recode12":"09","mother_bmi_recode":"9","mother_age_recode9":"2","f_count":49,"m_count":101},{"birth_weight_recode12":"09","mother_bmi_recode":"9","mother_age_recode9":"3","f_count":289,"m_count":539},{"birth_weight_recode12":"09","mother_bmi_recode":"9","mother_age_recode9":"4","f_count":579,"m_count":1040},{"birth_weight_recode12":"09","mother_bmi_recode":"9","mother_age_recode9":"5","f_count":708,"m_count":1197},{"birth_weight_recode12":"09","mother_bmi_recode":"9","mother_age_recode9":"6","f_count":426,"m_count":652},{"birth_weight_recode12":"09","mother_bmi_recode":"9","mother_age_recode9":"7","f_count":101,"m_count":143},{"birth_weight_recode12":"09","mother_bmi_recode":"9","mother_age_recode9":"8","f_count":8,"m_count":13},{"birth_weight_recode12":"10","mother_bmi_recode":"1","mother_age_recode9":"2","f_count":7,"m_count":15},{"birth_weight_recode12":"10","mother_bmi_recode":"1","mother_age_recode9":"3","f_count":20,"m_count":34},{"birth_weight_recode12":"10","mother_bmi_recode":"1","mother_age_recode9":"4","f_count":19,"m_count":55},{"birth_weight_recode12":"10","mother_bmi_recode":"1","mother_age_recode9":"5","f_count":19,"m_count":68},{"birth_weight_recode12":"10","mother_bmi_recode":"1","mother_age_recode9":"6","f_count":10,"m_count":29},{"birth_weight_recode12":"10","mother_bmi_recode":"2","mother_age_recode9":"2","f_count":78,"m_count":183},{"birth_weight_recode12":"10","mother_bmi_recode":"2","mother_age_recode9":"3","f_count":331,"m_count":857},{"birth_weight_recode12":"10","mother_bmi_recode":"2","mother_age_recode9":"4","f_count":734,"m_count":1876},{"birth_weight_recode12":"10","mother_bmi_recode":"2","mother_age_recode9":"5","f_count":967,"m_count":2404},{"birth_weight_recode12":"10","mother_bmi_recode":"2","mother_age_recode9":"6","f_count":492,"m_count":1220},{"birth_weight_recode12":"10","mother_bmi_recode":"2","mother_age_recode9":"7","f_count":77,"m_count":219},{"birth_weight_recode12":"10","mother_bmi_recode":"2","mother_age_recode9":"8","f_count":1,"m_count":15},{"birth_weight_recode12":"10","mother_bmi_recode":"2","mother_age_recode9":"9","f_count":1,"m_count":2},{"birth_weight_recode12":"10","mother_bmi_recode":"3","mother_age_recode9":"2","f_count":78,"m_count":135},{"birth_weight_recode12":"10","mother_bmi_recode":"3","mother_age_recode9":"3","f_count":397,"m_count":900},{"birth_weight_recode12":"10","mother_bmi_recode":"3","mother_age_recode9":"4","f_count":846,"m_count":1887},{"birth_weight_recode12":"10","mother_bmi_recode":"3","mother_age_recode9":"5","f_count":1093,"m_count":2429},{"birth_weight_recode12":"10","mother_bmi_recode":"3","mother_age_recode9":"6","f_count":624,"m_count":1273},{"birth_weight_recode12":"10","mother_bmi_recode":"3","mother_age_recode9":"7","f_count":129,"m_count":261},{"birth_weight_recode12":"10","mother_bmi_recode":"3","mother_age_recode9":"8","f_count":5,"m_count":12},{"birth_weight_recode12":"10","mother_bmi_recode":"4","mother_age_recode9":"2","f_count":44,"m_count":83},{"birth_weight_recode12":"10","mother_bmi_recode":"4","mother_age_recode9":"3","f_count":347,"m_count":678},{"birth_weight_recode12":"10","mother_bmi_recode":"4","mother_age_recode9":"4","f_count":684,"m_count":1430},{"birth_weight_recode12":"10","mother_bmi_recode":"4","mother_age_recode9":"5","f_count":795,"m_count":1576},{"birth_weight_recode12":"10","mother_bmi_recode":"4","mother_age_recode9":"6","f_count":472,"m_count":904},{"birth_weight_recode12":"10","mother_bmi_recode":"4","mother_age_recode9":"7","f_count":93,"m_count":186},{"birth_weight_recode12":"10","mother_bmi_recode":"4","mother_age_recode9":"8","f_count":7,"m_count":3},{"birth_weight_recode12":"10","mother_bmi_recode":"5","mother_age_recode9":"2","f_count":21,"m_count":57},{"birth_weight_recode12":"10","mother_bmi_recode":"5","mother_age_recode9":"3","f_count":206,"m_count":418},{"birth_weight_recode12":"10","mother_bmi_recode":"5","mother_age_recode9":"4","f_count":480,"m_count":847},{"birth_weight_recode12":"10","mother_bmi_recode":"5","mother_age_recode9":"5","f_count":504,"m_count":998},{"birth_weight_recode12":"10","mother_bmi_recode":"5","mother_age_recode9":"6","f_count":295,"m_count":521},{"birth_weight_recode12":"10","mother_bmi_recode":"5","mother_age_recode9":"7","f_count":56,"m_count":107},{"birth_weight_recode12":"10","mother_bmi_recode":"5","mother_age_recode9":"8","f_count":2,"m_count":6},{"birth_weight_recode12":"10","mother_bmi_recode":"6","mother_age_recode9":"2","f_count":25,"m_count":33},{"birth_weight_recode12":"10","mother_bmi_recode":"6","mother_age_recode9":"3","f_count":189,"m_count":365},{"birth_weight_recode12":"10","mother_bmi_recode":"6","mother_age_recode9":"4","f_count":499,"m_count":735},{"birth_weight_recode12":"10","mother_bmi_recode":"6","mother_age_recode9":"5","f_count":451,"m_count":800},{"birth_weight_recode12":"10","mother_bmi_recode":"6","mother_age_recode9":"6","f_count":285,"m_count":446},{"birth_weight_recode12":"10","mother_bmi_recode":"6","mother_age_recode9":"7","f_count":58,"m_count":92},{"birth_weight_recode12":"10","mother_bmi_recode":"6","mother_age_recode9":"8","f_count":2,"m_count":4},{"birth_weight_recode12":"10","mother_bmi_recode":"9","mother_age_recode9":"2","f_count":5,"m_count":6},{"birth_weight_recode12":"10","mother_bmi_recode":"9","mother_age_recode9":"3","f_count":38,"m_count":82},{"birth_weight_recode12":"10","mother_bmi_recode":"9","mother_age_recode9":"4","f_count":64,"m_count":199},{"birth_weight_recode12":"10","mother_bmi_recode":"9","mother_age_recode9":"5","f_count":100,"m_count":197},{"birth_weight_recode12":"10","mother_bmi_recode":"9","mother_age_recode9":"6","f_count":61,"m_count":131},{"birth_weight_recode12":"10","mother_bmi_recode":"9","mother_age_recode9":"7","f_count":13,"m_count":33},{"birth_weight_recode12":"10","mother_bmi_recode":"9","mother_age_recode9":"8","f_count":3,"m_count":4},{"birth_weight_recode12":"11","mother_bmi_recode":"1","mother_age_recode9":"3","f_count":4,"m_count":1},{"birth_weight_recode12":"11","mother_bmi_recode":"1","mother_age_recode9":"4","f_count":4,"m_count":5},{"birth_weight_recode12":"11","mother_bmi_recode":"1","mother_age_recode9":"5","f_count":3,"m_count":4},{"birth_weight_recode12":"11","mother_bmi_recode":"2","mother_age_recode9":"2","f_count":11,"m_count":15},{"birth_weight_recode12":"11","mother_bmi_recode":"2","mother_age_recode9":"3","f_count":29,"m_count":70},{"birth_weight_recode12":"11","mother_bmi_recode":"2","mother_age_recode9":"4","f_count":62,"m_count":142},{"birth_weight_recode12":"11","mother_bmi_recode":"2","mother_age_recode9":"5","f_count":72,"m_count":176},{"birth_weight_recode12":"11","mother_bmi_recode":"2","mother_age_recode9":"6","f_count":47,"m_count":113},{"birth_weight_recode12":"11","mother_bmi_recode":"2","mother_age_recode9":"7","f_count":8,"m_count":17},{"birth_weight_recode12":"11","mother_bmi_recode":"3","mother_age_recode9":"2","f_count":7,"m_count":11},{"birth_weight_recode12":"11","mother_bmi_recode":"3","mother_age_recode9":"3","f_count":35,"m_count":81},{"birth_weight_recode12":"11","mother_bmi_recode":"3","mother_age_recode9":"4","f_count":88,"m_count":186},{"birth_weight_recode12":"11","mother_bmi_recode":"3","mother_age_recode9":"5","f_count":108,"m_count":248},{"birth_weight_recode12":"11","mother_bmi_recode":"3","mother_age_recode9":"6","f_count":58,"m_count":143},{"birth_weight_recode12":"11","mother_bmi_recode":"3","mother_age_recode9":"7","f_count":18,"m_count":31},{"birth_weight_recode12":"11","mother_bmi_recode":"3","mother_age_recode9":"8","f_count":1,"m_count":3},{"birth_weight_recode12":"11","mother_bmi_recode":"4","mother_age_recode9":"2","f_count":7,"m_count":5},{"birth_weight_recode12":"11","mother_bmi_recode":"4","mother_age_recode9":"3","f_count":38,"m_count":90},{"birth_weight_recode12":"11","mother_bmi_recode":"4","mother_age_recode9":"4","f_count":61,"m_count":168},{"birth_weight_recode12":"11","mother_bmi_recode":"4","mother_age_recode9":"5","f_count":96,"m_count":198},{"birth_weight_recode12":"11","mother_bmi_recode":"4","mother_age_recode9":"6","f_count":66,"m_count":122},{"birth_weight_recode12":"11","mother_bmi_recode":"4","mother_age_recode9":"7","f_count":12,"m_count":28},{"birth_weight_recode12":"11","mother_bmi_recode":"4","mother_age_recode9":"8","f_count":1,"m_count":2},{"birth_weight_recode12":"11","mother_bmi_recode":"5","mother_age_recode9":"3","f_count":26,"m_count":55},{"birth_weight_recode12":"11","mother_bmi_recode":"5","mother_age_recode9":"4","f_count":63,"m_count":120},{"birth_weight_recode12":"11","mother_bmi_recode":"5","mother_age_recode9":"5","f_count":88,"m_count":149},{"birth_weight_recode12":"11","mother_bmi_recode":"5","mother_age_recode9":"6","f_count":48,"m_count":75},{"birth_weight_recode12":"11","mother_bmi_recode":"5","mother_age_recode9":"7","f_count":7,"m_count":19},{"birth_weight_recode12":"11","mother_bmi_recode":"6","mother_age_recode9":"2","f_count":3,"m_count":4},{"birth_weight_recode12":"11","mother_bmi_recode":"6","mother_age_recode9":"3","f_count":29,"m_count":53},{"birth_weight_recode12":"11","mother_bmi_recode":"6","mother_age_recode9":"4","f_count":90,"m_count":136},{"birth_weight_recode12":"11","mother_bmi_recode":"6","mother_age_recode9":"5","f_count":88,"m_count":164},{"birth_weight_recode12":"11","mother_bmi_recode":"6","mother_age_recode9":"6","f_count":51,"m_count":102},{"birth_weight_recode12":"11","mother_bmi_recode":"6","mother_age_recode9":"7","f_count":9,"m_count":25},{"birth_weight_recode12":"11","mother_bmi_recode":"6","mother_age_recode9":"8","f_count":1,"m_count":1},{"birth_weight_recode12":"11","mother_bmi_recode":"9","mother_age_recode9":"3","f_count":4,"m_count":12},{"birth_weight_recode12":"11","mother_bmi_recode":"9","mother_age_recode9":"4","f_count":9,"m_count":24},{"birth_weight_recode12":"11","mother_bmi_recode":"9","mother_age_recode9":"5","f_count":17,"m_count":34},{"birth_weight_recode12":"11","mother_bmi_recode":"9","mother_age_recode9":"6","f_count":8,"m_count":16},{"birth_weight_recode12":"11","mother_bmi_recode":"9","mother_age_recode9":"7","f_count":1,"m_count":2},{"birth_weight_recode12":"12","mother_bmi_recode":"1","mother_age_recode9":"2","f_count":2,"m_count":6},{"birth_weight_recode12":"12","mother_bmi_recode":"1","mother_age_recode9":"3","f_count":6,"m_count":14},{"birth_weight_recode12":"12","mother_bmi_recode":"1","mother_age_recode9":"4","f_count":6,"m_count":12},{"birth_weight_recode12":"12","mother_bmi_recode":"1","mother_age_recode9":"5","f_count":6,"m_count":10},{"birth_weight_recode12":"12","mother_bmi_recode":"1","mother_age_recode9":"6","f_count":4,"m_count":2},{"birth_weight_recode12":"12","mother_bmi_recode":"1","mother_age_recode9":"7","f_count":1,"m_count":3},{"birth_weight_recode12":"12","mother_bmi_recode":"2","mother_age_recode9":"2","f_count":14,"m_count":34},{"birth_weight_recode12":"12","mother_bmi_recode":"2","mother_age_recode9":"3","f_count":81,"m_count":76},{"birth_weight_recode12":"12","mother_bmi_recode":"2","mother_age_recode9":"4","f_count":103,"m_count":122},{"birth_weight_recode12":"12","mother_bmi_recode":"2","mother_age_recode9":"5","f_count":120,"m_count":122},{"birth_weight_recode12":"12","mother_bmi_recode":"2","mother_age_recode9":"6","f_count":44,"m_count":68},{"birth_weight_recode12":"12","mother_bmi_recode":"2","mother_age_recode9":"7","f_count":10,"m_count":17},{"birth_weight_recode12":"12","mother_bmi_recode":"3","mother_age_recode9":"2","f_count":9,"m_count":15},{"birth_weight_recode12":"12","mother_bmi_recode":"3","mother_age_recode9":"3","f_count":47,"m_count":41},{"birth_weight_recode12":"12","mother_bmi_recode":"3","mother_age_recode9":"4","f_count":68,"m_count":77},{"birth_weight_recode12":"12","mother_bmi_recode":"3","mother_age_recode9":"5","f_count":62,"m_count":61},{"birth_weight_recode12":"12","mother_bmi_recode":"3","mother_age_recode9":"6","f_count":47,"m_count":38},{"birth_weight_recode12":"12","mother_bmi_recode":"3","mother_age_recode9":"7","f_count":8,"m_count":9},{"birth_weight_recode12":"12","mother_bmi_recode":"3","mother_age_recode9":"8","f_count":1,"m_count":1},{"birth_weight_recode12":"12","mother_bmi_recode":"4","mother_age_recode9":"2","f_count":8,"m_count":8},{"birth_weight_recode12":"12","mother_bmi_recode":"4","mother_age_recode9":"3","f_count":28,"m_count":37},{"birth_weight_recode12":"12","mother_bmi_recode":"4","mother_age_recode9":"4","f_count":48,"m_count":62},{"birth_weight_recode12":"12","mother_bmi_recode":"4","mother_age_recode9":"5","f_count":41,"m_count":55},{"birth_weight_recode12":"12","mother_bmi_recode":"4","mother_age_recode9":"6","f_count":35,"m_count":27},{"birth_weight_recode12":"12","mother_bmi_recode":"4","mother_age_recode9":"7","f_count":8,"m_count":12},{"birth_weight_recode12":"12","mother_bmi_recode":"5","mother_age_recode9":"2","f_count":3,"m_count":3},{"birth_weight_recode12":"12","mother_bmi_recode":"5","mother_age_recode9":"3","f_count":11,"m_count":29},{"birth_weight_recode12":"12","mother_bmi_recode":"5","mother_age_recode9":"4","f_count":32,"m_count":33},{"birth_weight_recode12":"12","mother_bmi_recode":"5","mother_age_recode9":"5","f_count":18,"m_count":21},{"birth_weight_recode12":"12","mother_bmi_recode":"5","mother_age_recode9":"6","f_count":11,"m_count":13},{"birth_weight_recode12":"12","mother_bmi_recode":"5","mother_age_recode9":"7","f_count":2,"m_count":4},{"birth_weight_recode12":"12","mother_bmi_recode":"6","mother_age_recode9":"2","f_count":1,"m_count":2},{"birth_weight_recode12":"12","mother_bmi_recode":"6","mother_age_recode9":"3","f_count":11,"m_count":23},{"birth_weight_recode12":"12","mother_bmi_recode":"6","mother_age_recode9":"4","f_count":22,"m_count":36},{"birth_weight_recode12":"12","mother_bmi_recode":"6","mother_age_recode9":"5","f_count":18,"m_count":24},{"birth_weight_recode12":"12","mother_bmi_recode":"6","mother_age_recode9":"6","f_count":6,"m_count":8},{"birth_weight_recode12":"12","mother_bmi_recode":"6","mother_age_recode9":"7","f_count":2,"m_count":3},{"birth_weight_recode12":"12","mother_bmi_recode":"9","mother_age_recode9":"2","f_count":11,"m_count":25},{"birth_weight_recode12":"12","mother_bmi_recode":"9","mother_age_recode9":"3","f_count":97,"m_count":97},{"birth_weight_recode12":"12","mother_bmi_recode":"9","mother_age_recode9":"4","f_count":142,"m_count":179},{"birth_weight_recode12":"12","mother_bmi_recode":"9","mother_age_recode9":"5","f_count":108,"m_count":118},{"birth_weight_recode12":"12","mother_bmi_recode":"9","mother_age_recode9":"6","f_count":64,"m_count":81},{"birth_weight_recode12":"12","mother_bmi_recode":"9","mother_age_recode9":"7","f_count":13,"m_count":16},{"birth_weight_recode12":"12","mother_bmi_recode":"9","mother_age_recode9":"8","f_count":1,"m_count":1}]